{
  "fetched_at_utc": "2026-07-19T13:09:00Z",
  "location": {
    "weather": "La Mesa, CA 91942 (NWS SGX point forecast)",
    "surf": "Mission Beach / Pacific Beach, San Diego"
  },
  "weather": {
    "updated": "2026-07-19T07:03:33+00:00",
    "periods": [
      {
        "name": "Overnight",
        "temperature": 66,
        "temperatureUnit": "F",
        "windSpeed": "0 mph",
        "windDirection": "",
        "shortForecast": "Patchy Fog",
        "detailedForecast": "Patchy fog. Mostly cloudy, with a low around 66. West wind around 0 mph.",
        "precipChancePct": 2
      },
      {
        "name": "Sunday",
        "temperature": 84,
        "temperatureUnit": "F",
        "windSpeed": "0 to 10 mph",
        "windDirection": "W",
        "shortForecast": "Patchy Fog then Mostly Sunny",
        "detailedForecast": "Patchy fog before 11am. Mostly sunny, with a high near 84. West wind 0 to 10 mph.",
        "precipChancePct": 3
      },
      {
        "name": "Sunday Night",
        "temperature": 65,
        "temperatureUnit": "F",
        "windSpeed": "0 to 5 mph",
        "windDirection": "W",
        "shortForecast": "Partly Cloudy then Patchy Fog",
        "detailedForecast": "Patchy fog after 5am. Partly cloudy, with a low around 65. West wind 0 to 5 mph.",
        "precipChancePct": 3
      },
      {
        "name": "Monday",
        "temperature": 85,
        "temperatureUnit": "F",
        "windSpeed": "0 to 10 mph",
        "windDirection": "W",
        "shortForecast": "Patchy Fog then Mostly Sunny",
        "detailedForecast": "Patchy fog before 11am. Mostly sunny, with a high near 85. West wind 0 to 10 mph.",
        "precipChancePct": 2
      }
    ]
  },
  "buoy_46258_mission_bay": {
    "observed_utc": "2026-07-19T12:26Z",
    "waveHeightFt": 3.9,
    "dominantPeriodS": 13,
    "avgPeriodS": 9.2,
    "meanWaveDirDeg": 183,
    "waterTempF": 71.1
  },
  "buoy_46225_torrey_pines": {
    "observed_utc": "2026-07-19T12:26Z",
    "waveHeightFt": 3.6,
    "dominantPeriodS": 13,
    "avgPeriodS": 9.5,
    "meanWaveDirDeg": 185,
    "waterTempF": 71.2
  },
  "tides_san_diego_9410170": [
    {
      "time_pt": "2026-07-19 01:01",
      "type": "High",
      "heightFt": 4.959
    },
    {
      "time_pt": "2026-07-19 07:31",
      "type": "Low",
      "heightFt": 0.604
    },
    {
      "time_pt": "2026-07-19 14:13",
      "type": "High",
      "heightFt": 5.085
    },
    {
      "time_pt": "2026-07-19 20:24",
      "type": "Low",
      "heightFt": 1.937
    },
    {
      "time_pt": "2026-07-20 02:01",
      "type": "High",
      "heightFt": 4.069
    },
    {
      "time_pt": "2026-07-20 08:06",
      "type": "Low",
      "heightFt": 1.329
    },
    {
      "time_pt": "2026-07-20 15:02",
      "type": "High",
      "heightFt": 5.117
    },
    {
      "time_pt": "2026-07-20 21:54",
      "type": "Low",
      "heightFt": 1.844
    }
  ]
}
